xoa_converter/__init__.py
xoa_converter/entry.py
xoa_converter/exceptions.py
xoa_converter/types.py
xoa_converter/converters/__init__.py
xoa_converter/converters/common.py
xoa_converter/converters/fabric.py
xoa_converter/converters/rfc2544/__init__.py
xoa_converter/converters/rfc2544/adapter.py
xoa_converter/converters/rfc2544/enums.py
xoa_converter/converters/rfc2544/model.py
xoa_converter/converters/rfc2889/__init__.py
xoa_converter/converters/rfc2889/adapter.py
xoa_converter/converters/rfc2889/const.py
xoa_converter/converters/rfc2889/model.py
xoa_converter/converters/rfc3918/__init__.py
xoa_converter/converters/rfc3918/adapter.py
xoa_converter/converters/rfc3918/const_conv.py
xoa_converter/converters/rfc3918/field.py
xoa_converter/converters/rfc3918/legacy.py
xoa_converter/converters/segment_refs/arp.json
xoa_converter/converters/segment_refs/ecpri.json
xoa_converter/converters/segment_refs/ethernet.json
xoa_converter/converters/segment_refs/ethernet802.3.json
xoa_converter/converters/segment_refs/fcoe.json
xoa_converter/converters/segment_refs/fcoetail.json
xoa_converter/converters/segment_refs/fiberchannel.json
xoa_converter/converters/segment_refs/geneve.json
xoa_converter/converters/segment_refs/grecheck.json
xoa_converter/converters/segment_refs/grenocheck.json
xoa_converter/converters/segment_refs/gtpv1.json
xoa_converter/converters/segment_refs/gtpv1l0.json
xoa_converter/converters/segment_refs/gtpv1l1.json
xoa_converter/converters/segment_refs/gtpv2l0.json
xoa_converter/converters/segment_refs/gtpv2l1.json
xoa_converter/converters/segment_refs/icmp.json
xoa_converter/converters/segment_refs/icmpv6.json
xoa_converter/converters/segment_refs/igmpv1.json
xoa_converter/converters/segment_refs/igmpv2.json
xoa_converter/converters/segment_refs/igmpv3grouprecord.json
xoa_converter/converters/segment_refs/igmpv3l0.json
xoa_converter/converters/segment_refs/igmpv3l1.json
xoa_converter/converters/segment_refs/igmpv3memreport.json
xoa_converter-2.0.7.dist-info/LICENSE
xoa_converter-2.0.7.dist-info/METADATA
xoa_converter-2.0.7.dist-info/WHEEL
xoa_converter-2.0.7.dist-info/top_level.txt
xoa_converter-2.0.7.dist-info/RECORD
