Metadata-Version: 2.1
Name: xoa-converter
Version: 2.0.7
Summary: Xena OpenAutomation test configuration converter let you easily migrate your Valkyrie test suites config files (.v2544, .v2889, .v3918, and .v1564) into XOA.
Home-page: https://github.com/xenanetworks/open-automation-config-converter
Author: Frank Chen, Maureen Chen, Artem Constantinov
Author-email: fch@xenanewtorks.com, mch@xenanetworks.com, aco@xenanetworks.com
Maintainer: Xena Networks
Maintainer-email: support@xenanetworks.com
License: Apache 2.0
Classifier: Development Status :: 5 - Production/Stable
Classifier: Intended Audience :: Developers
Classifier: Topic :: Software Development :: Libraries :: Python Modules
Classifier: License :: OSI Approved :: Apache Software License
Classifier: Programming Language :: Python :: 3.8
Classifier: Programming Language :: Python :: 3.9
Classifier: Programming Language :: Python :: 3.10
Requires-Python: >=3.8.9
License-File: LICENSE
Requires-Dist: pydantic>=1.8.2
Requires-Dist: datamodel-code-generator
